{
  "products": [
    {
      "id": 1,
      "name": "Samsung Galaxy A36 5G 8GB 128GB",
      "brand": "samsung",
      "category": "dienthoai",
      "price": 8490000,
      "oldPrice": 9490000,
      "discount": 10,
      "ram": 8,
      "storage": 128,
      "screen": "6.6\" Super AMOLED FHD+",
      "camera": "50MP OIS",
      "battery": "5000 mAh",
      "os": "Android 15",
      "features": ["tragop", "freeship"],
      "colors": ["#e8f5e9", "#000000", "#1e3a5f"],
      "image": "images/samsung_galaxy_a36_5g.avif",
      "images": [
        "images/samsung_galaxy_a36_5g.avif",
        "images/samsung-galaxy-s24_15__2.webp",
        "images/samsung-galaxy-s24_17__2.webp",
        "images/samsung-galaxy-s24_20__2.webp"
      ],
      "sku": "SSG-A36-5G-128",
      "rating": 4.5,
      "reviews": 152
    },
    {
      "id": 2,
      "name": "Samsung Galaxy A56 5G 8GB 256GB",
      "brand": "samsung",
      "category": "dienthoai",
      "price": 9690000,
      "oldPrice": 10690000,
      "discount": 9,
      "ram": 8,
      "storage": 256,
      "screen": "6.7\" Super AMOLED FHD+",
      "camera": "50MP OIS",
      "battery": "5000 mAh",
      "os": "Android 15",
      "features": ["tragop", "freeship"],
      "colors": ["#4fc3f7", "#000000", "#e8f5e9"],
      "image": "images/A56.avif",
      "images": [
        "images/A56.avif",
        "images/samsung-galaxy-s24_15__2.webp",
        "images/samsung-galaxy-s24_17__2.webp",
        "images/samsung-galaxy-s24_20__2.webp"
      ],
      "sku": "SSG-A56-5G-256",
      "rating": 4.6,
      "reviews": 234
    },
    {
      "id": 3,
      "name": "Samsung Galaxy A16 5G 4GB 128GB",
      "brand": "samsung",
      "category": "dienthoai",
      "price": 3990000,
      "oldPrice": 4990000,
      "discount": 20,
      "ram": 4,
      "storage": 128,
      "screen": "6.7\" Super AMOLED FHD+",
      "camera": "50MP",
      "battery": "5000 mAh",
      "os": "Android 14",
      "features": ["tragop", "freeship"],
      "colors": ["#000000", "#e0e0e0", "#1e3a5f"],
      "image": "images/A16.avif",
      "images": [
        "images/A16.avif",
        "images/A17.avif",
        "images/samsung-galaxy-s24_15__2.webp",
        "images/samsung-galaxy-s24_17__2.webp"
      ],
      "sku": "SSG-A16-5G-128",
      "rating": 4.4,
      "reviews": 189
    },
    {
      "id": 4,
      "name": "Samsung Galaxy A17 5G 8GB 128GB",
      "brand": "samsung",
      "category": "dienthoai",
      "price": 4599000,
      "oldPrice": 6590000,
      "discount": 30,
      "ram": 8,
      "storage": 128,
      "screen": "6.7\" Super AMOLED",
      "camera": "50MP",
      "battery": "5000 mAh",
      "os": "Android 14",
      "features": ["tragop"],
      "colors": ["#000000", "#4fc3f7"],
      "image": "images/A17.avif",
      "images": [
        "images/A17.avif",
        "images/A16.avif",
        "images/samsung-galaxy-s24_15__2.webp",
        "images/samsung-galaxy-s24_20__2.webp"
      ],
      "sku": "SSG-A17-5G-128",
      "rating": 4.3,
      "reviews": 87
    },
    {
      "id": 5,
      "name": "iPhone 15 Pro Max 256GB Titan",
      "brand": "apple",
      "category": "dienthoai",
      "price": 28990000,
      "oldPrice": 34990000,
      "discount": 17,
      "ram": 8,
      "storage": 256,
      "screen": "6.7\" Super Retina XDR OLED",
      "camera": "48MP Pro Camera",
      "battery": "4422 mAh",
      "os": "iOS 17",
      "features": ["tragop", "freeship"],
      "colors": ["#4a4a4a", "#e8e8e8", "#1e3a5f", "#ffd700"],
      "image": "images/15-256.avif",
      "images": [
        "images/15-256.avif",
        "images/iphone-15-pro-max-256-99.png",
        "images/15IP.avif",
        "images/iphone-14-pro-max-128-99.webp"
      ],
      "sku": "APL-IP15PM-256",
      "rating": 4.9,
      "reviews": 512
    },
    {
      "id": 6,
      "name": "iPhone 15 Plus 128GB",
      "brand": "apple",
      "category": "dienthoai",
      "price": 22990000,
      "oldPrice": 25990000,
      "discount": 11,
      "ram": 6,
      "storage": 128,
      "screen": "6.7\" Super Retina XDR",
      "camera": "48MP",
      "battery": "4383 mAh",
      "os": "iOS 17",
      "features": ["tragop", "freeship"],
      "colors": ["#f48fb1", "#000000", "#e3f2fd", "#ffd700"],
      "image": "images/15IP.avif",
      "images": [
        "images/15IP.avif",
        "images/15-256.avif",
        "images/iphone-15-pro-max-256-99.png",
        "images/iphone-14-pro-max-128-99.webp"
      ],
      "sku": "APL-IP15P-128",
      "rating": 4.7,
      "reviews": 345
    },
    {
      "id": 7,
      "name": "iPhone 17 Pro Max 256GB",
      "brand": "apple",
      "category": "dienthoai",
      "price": 33990000,
      "oldPrice": null,
      "discount": 0,
      "ram": 12,
      "storage": 256,
      "screen": "6.9\" ProMotion OLED",
      "camera": "48MP Fusion Camera",
      "battery": "4685 mAh",
      "os": "iOS 18",
      "features": ["tragop", "freeship"],
      "colors": ["#5e6e76", "#f2f1eb", "#000000"],
      "image": "images/iphone17.avif",
      "images": [
        "images/iphone17.avif",
        "images/iphone-17-pro_1.webp",
        "images/iphone-17-pro-1_1.webp",
        "images/iphone-17-pro-2_1_1.webp"
      ],
      "sku": "APL-IP17PM-256",
      "rating": 4.9,
      "reviews": 89
    },
    {
      "id": 8,
      "name": "iPhone 14 Pro Max 128GB - Like New 99%",
      "brand": "apple",
      "category": "dienthoai",
      "price": 16390000,
      "oldPrice": 27990000,
      "discount": 41,
      "ram": 6,
      "storage": 128,
      "screen": "6.7\" Super Retina XDR",
      "camera": "48MP",
      "battery": "4323 mAh",
      "os": "iOS 17",
      "features": ["tragop"],
      "colors": ["#4a148c", "#000000", "#ffd700"],
      "image": "images/iphone-14-pro-max-128-99.webp",
      "images": [
        "images/iphone-14-pro-max-128-99.webp",
        "images/15-256.avif",
        "images/15IP.avif",
        "images/iphone-15-pro-max-256-99.png"
      ],
      "sku": "APL-IP14PM-128-LN",
      "rating": 4.6,
      "reviews": 267
    },
    {
      "id": 9,
      "name": "Samsung Galaxy S25 Ultra 12GB 256GB",
      "brand": "samsung",
      "category": "dienthoai",
      "price": 31990000,
      "oldPrice": 35990000,
      "discount": 11,
      "ram": 12,
      "storage": 256,
      "screen": "6.8\" Dynamic AMOLED 2X QHD+",
      "camera": "200MP AI Camera",
      "battery": "5000 mAh",
      "os": "Android 15 One UI 7",
      "features": ["tragop", "freeship"],
      "colors": ["#9e9e9e", "#000000", "#1e3a5f"],
      "image": "images/samsung.webp",
      "images": [
        "images/samsung.webp",
        "images/samsung-galaxy-s24_15__2.webp",
        "images/samsung-galaxy-s24_17__2.webp",
        "images/samsung-galaxy-s24_20__2.webp"
      ],
      "sku": "SSG-S25U-256",
      "rating": 4.8,
      "reviews": 687
    },
    {
      "id": 10,
      "name": "Samsung Galaxy S24 FE 5G 8GB 128GB",
      "brand": "samsung",
      "category": "dienthoai",
      "price": 14990000,
      "oldPrice": 16990000,
      "discount": 12,
      "ram": 8,
      "storage": 128,
      "screen": "6.7\" Dynamic AMOLED 2X",
      "camera": "50MP OIS",
      "battery": "4700 mAh",
      "os": "Android 14",
      "features": ["tragop", "freeship"],
      "colors": ["#000000", "#e0e0e0", "#4fc3f7"],
      "image": "images/samsung_galaxy_s24_fe_5g.avif",
      "images": [
        "images/samsung_galaxy_s24_fe_5g.avif",
        "images/25fe.png",
        "images/samsung-galaxy-s24_15__2.webp",
        "images/samsung-galaxy-s24_17__2.webp"
      ],
      "sku": "SSG-S24FE-128",
      "rating": 4.7,
      "reviews": 421
    },
    {
      "id": 11,
      "name": "Samsung Galaxy S24 Plus 12GB 256GB",
      "brand": "samsung",
      "category": "dienthoai",
      "price": 22990000,
      "oldPrice": 25990000,
      "discount": 12,
      "ram": 12,
      "storage": 256,
      "screen": "6.7\" Dynamic AMOLED 2X QHD+",
      "camera": "50MP OIS",
      "battery": "4900 mAh",
      "os": "Android 14",
      "features": ["tragop", "freeship"],
      "colors": ["#000000", "#ffd700"],
      "image": "images/galaxy-s24-plus-den.webp",
      "images": [
        "images/galaxy-s24-plus-den.webp",
        "images/galaxy-s24-plus-vang.webp",
        "images/samsung-galaxy-s24_15__2.webp",
        "images/samsung-galaxy-s24_17__2.webp"
      ],
      "sku": "SSG-S24P-256",
      "rating": 4.8,
      "reviews": 356
    },
    {
      "id": 12,
      "name": "OPPO Reno 12 F 5G 8GB 256GB",
      "brand": "oppo",
      "category": "dienthoai",
      "price": 8990000,
      "oldPrice": 9990000,
      "discount": 10,
      "ram": 8,
      "storage": 256,
      "screen": "6.67\" AMOLED FHD+",
      "camera": "50MP AI Camera",
      "battery": "5000 mAh",
      "os": "Android 14 ColorOS 14",
      "features": ["tragop", "freeship"],
      "colors": ["#ff9800", "#9c27b0", "#000000"],
      "image": "images/oppo-reno.avif",
      "images": [
        "images/oppo-reno.avif",
        "images/reno-xanh.avif",
        "images/reno10_5g_-_combo_product_-_blue_-_copy.webp",
        "images/reno10-5g-860_720.webp"
      ],
      "sku": "OPO-R12F-256",
      "rating": 4.4,
      "reviews": 178
    },
    {
      "id": 13,
      "name": "OPPO Find X9 Pro 12GB 256GB",
      "brand": "oppo",
      "category": "dienthoai",
      "price": 21990000,
      "oldPrice": 24990000,
      "discount": 12,
      "ram": 12,
      "storage": 256,
      "screen": "6.82\" LTPO AMOLED 2K",
      "camera": "50MP Hasselblad",
      "battery": "5400 mAh",
      "os": "Android 15 ColorOS 15",
      "features": ["tragop", "freeship"],
      "colors": ["#000000", "#ffeb3b"],
      "image": "images/oppx9.avif",
      "images": [
        "images/oppx9.avif",
        "images/oppo-find-x9-cate-open-sale.webp",
        "images/oppo-reno.avif",
        "images/reno-xanh.avif"
      ],
      "sku": "OPO-FX9P-256",
      "rating": 4.8,
      "reviews": 156
    },
    {
      "id": 14,
      "name": "OPPO Reno 13 F 4G 8GB 256GB",
      "brand": "oppo",
      "category": "dienthoai",
      "price": 7990000,
      "oldPrice": 8990000,
      "discount": 11,
      "ram": 8,
      "storage": 256,
      "screen": "6.67\" AMOLED",
      "camera": "64MP",
      "battery": "5000 mAh",
      "os": "Android 14",
      "features": ["tragop"],
      "colors": ["#000000", "#4caf50"],
      "image": "images/oppo_reno_13_f_4g_256gb.avif",
      "images": [
        "images/oppo_reno_13_f_4g_256gb.avif",
        "images/oppo-reno.avif",
        "images/reno-xanh.avif",
        "images/reno10_5g_-_combo_product_-_blue_-_copy.webp"
      ],
      "sku": "OPO-R13F-256",
      "rating": 4.3,
      "reviews": 98
    },
    {
      "id": 15,
      "name": "Xiaomi 14 5G 12GB 512GB",
      "brand": "xiaomi",
      "category": "dienthoai",
      "price": 19990000,
      "oldPrice": 24990000,
      "discount": 20,
      "ram": 12,
      "storage": 512,
      "screen": "6.36\" LTPO AMOLED",
      "camera": "50MP Leica",
      "battery": "4610 mAh",
      "os": "Android 14 HyperOS",
      "features": ["tragop", "freeship"],
      "colors": ["#81c784", "#000000", "#ffffff"],
      "image": "images/Xiaomi.avif",
      "images": [
        "images/Xiaomi.avif",
        "images/home-poco-f8-pro-1125.webp",
        "images/Xiaomi.avif",
        "images/home-poco-f8-pro-1125.webp"
      ],
      "sku": "XIA-14-512",
      "rating": 4.7,
      "reviews": 345
    },
    {
      "id": 16,
      "name": "Xiaomi POCO F8 Pro 12GB 256GB",
      "brand": "xiaomi",
      "category": "dienthoai",
      "price": 12990000,
      "oldPrice": 14990000,
      "discount": 13,
      "ram": 12,
      "storage": 256,
      "screen": "6.67\" AMOLED 2K",
      "camera": "50MP OIS",
      "battery": "5000 mAh",
      "os": "Android 14 HyperOS",
      "features": ["tragop", "freeship"],
      "colors": ["#000000", "#ffffff"],
      "image": "images/home-poco-f8-pro-1125.webp",
      "images": [
        "images/home-poco-f8-pro-1125.webp",
        "images/Xiaomi.avif",
        "images/home-poco-f8-pro-1125.webp",
        "images/Xiaomi.avif"
      ],
      "sku": "XIA-POCO-F8P-256",
      "rating": 4.6,
      "reviews": 234
    },
    {
      "id": 17,
      "name": "Google Pixel 9 Pro 12GB 128GB",
      "brand": "pixel",
      "category": "dienthoai",
      "price": 23990000,
      "oldPrice": null,
      "discount": 0,
      "ram": 12,
      "storage": 128,
      "screen": "6.3\" LTPO OLED",
      "camera": "50MP AI Camera",
      "battery": "4700 mAh",
      "os": "Android 15",
      "features": ["tragop", "freeship"],
      "colors": ["#f5f5f5", "#000000", "#e8f5e9"],
      "image": "images/pixel-9-pro.avif",
      "images": [
        "images/pixel-9-pro.avif",
        "images/pixel-9-pro.avif",
        "images/pixel-9-pro.avif",
        "images/pixel-9-pro.avif"
      ],
      "sku": "GOO-P9P-128",
      "rating": 4.8,
      "reviews": 234
    },
    {
      "id": 18,
      "name": "Sony Xperia 1 VI 12GB 256GB",
      "brand": "sony",
      "category": "dienthoai",
      "price": 29990000,
      "oldPrice": 32990000,
      "discount": 9,
      "ram": 12,
      "storage": 256,
      "screen": "6.5\" 4K HDR OLED",
      "camera": "48MP Zeiss T*",
      "battery": "5000 mAh",
      "os": "Android 14",
      "features": ["freeship"],
      "colors": ["#000000", "#333333"],
      "image": "images/sony-xperia-1-vi.webp",
      "images": [
        "images/sony-xperia-1-vi.webp",
        "images/cate_XPERIA_10VII_1125.webp",
        "images/sony-xperia-1-vi.webp",
        "images/cate_XPERIA_10VII_1125.webp"
      ],
      "sku": "SNY-X1VI-256",
      "rating": 4.6,
      "reviews": 89
    },
    {
      "id": 19,
      "name": "Sony Xperia 10 VII 8GB 128GB",
      "brand": "sony",
      "category": "dienthoai",
      "price": 10990000,
      "oldPrice": 11990000,
      "discount": 8,
      "ram": 8,
      "storage": 128,
      "screen": "6.1\" OLED 21:9",
      "camera": "48MP",
      "battery": "5000 mAh",
      "os": "Android 14",
      "features": ["tragop"],
      "colors": ["#ffffff", "#000000", "#1e3a5f"],
      "image": "images/cate_XPERIA_10VII_1125.webp",
      "images": [
        "images/cate_XPERIA_10VII_1125.webp",
        "images/sony-xperia-1-vi.webp",
        "images/cate_XPERIA_10VII_1125.webp",
        "images/sony-xperia-1-vi.webp"
      ],
      "sku": "SNY-X10VII-128",
      "rating": 4.4,
      "reviews": 67
    },
    {
      "id": 20,
      "name": "Tecno Pova 6 8GB 256GB",
      "brand": "tecno",
      "category": "dienthoai",
      "price": 5490000,
      "oldPrice": 6490000,
      "discount": 15,
      "ram": 8,
      "storage": 256,
      "screen": "6.78\" IPS LCD FHD+",
      "camera": "108MP",
      "battery": "6000 mAh",
      "os": "Android 14",
      "features": ["tragop"],
      "colors": ["#4caf50", "#000000"],
      "image": "images/TECNO.avif",
      "images": [
        "images/TECNO.avif",
        "images/TECNO.avif",
        "images/TECNO.avif",
        "images/TECNO.avif"
      ],
      "sku": "TEC-P6-256",
      "rating": 4.2,
      "reviews": 145
    }
  ]
}
